{"source":"https://jlcsearch.tscircuit.com/resistors/list.json (merged is_basic=true + per-package queries)","row_count":182,"rows":[{"lcsc":17168,"mfr":"0402WGF0000TCE","package":"0402","resistance":0,"tolerance_fraction":0.01,"tolerance_percent":1.0,"power_milliwatts":62.5,"power_watts":0.0625},{"lcsc":21189,"mfr":"0603WAF0000T5E","package":"0603","resistance":0,"tolerance_fraction":0.01,"tolerance_percent":1.0,"power_milliwatts":100.0,"power_watts":0.1},{"lcsc":17477,"mfr":"0805W8F0000T5E","package":"0805","resistance":0,"tolerance_fraction":0.01,"tolerance_percent":1.0,"power_milliwatts":125.0,"power_watts":0.125},{"lcsc":17888,"mfr":"1206W4F0000T5E","package":"1206","resistance":0,"tolerance_fraction":0.01,"tolerance_percent":1.0,"power_milliwatts":250.0,"power_watts":0.25},{"lcsc":25334,"mfr":"1206W4F100LT5E","package":"1206","resistance":0.1,"tolerance_fraction":0.01,"tolerance_percent":1.0,"power_milliwatts":250.0,"power_watts":0.25},{"lcsc":22936,"mfr":"0603WAF100KT5E","package":"0603","resistance":1,"tolerance_fraction":0.01,"tolerance_percent":1.0,"power_milliwatts":100.0,"power_watts":0.1},{"lcsc":25271,"mfr":"0805W8F100KT5E","package":"0805","resistance":1,"tolerance_fraction":0.01,"tolerance_percent":1.0,"power_milliwatts":125.0,"power_watts":0.125},{"lcsc":17928,"mfr":"1206W4F100KT5E","package":"1206","resistance":1,"tolerance_fraction":0.01,"tolerance_percent":1.0,"power_milliwatts":250.0,"power_watts":0.25},{"lcsc":22977,"mfr":"0603WAF200KT5E","package":"0603","resistance":2,"tolerance_fraction":0.01,"tolerance_percent":1.0,"power_milliwatts":100.0,"power_watts":0.1},{"lcsc":22939,"mfr":"0603WAF220KT5E","package":"0603","resistance":2.2,"tolerance_fraction":0.01,"tolerance_percent":1.0,"power_milliwatts":100.0,"power_watts":0.1},{"lcsc":17521,"mfr":"0805W8F220KT5E","package":"0805","resistance":2.2,"tolerance_fraction":0.01,"tolerance_percent":1.0,"power_milliwatts":125.0,"power_watts":0.125},{"lcsc":23164,"mfr":"0603WAF470KT5E","package":"0603","resistance":4.7,"tolerance_fraction":0.01,"tolerance_percent":1.0,"power_milliwatts":100.0,"power_watts":0.1},{"lcsc":17675,"mfr":"0805W8F470KT5E","package":"0805","resistance":4.7,"tolerance_fraction":0.01,"tolerance_percent":1.0,"power_milliwatts":125.0,"power_watts":0.125},{"lcsc":25197,"mfr":"0603WAF510KT5E","package":"0603","resistance":5.1,"tolerance_fraction":0.01,"tolerance_percent":1.0,"power_milliwatts":100.0,"power_watts":0.1},{"lcsc":17724,"mfr":"0805W8F510KT5E","package":"0805","resistance":5.1,"tolerance_fraction":0.01,"tolerance_percent":1.0,"power_milliwatts":125.0,"power_watts":0.125},{"lcsc":25077,"mfr":"0402WGF100JTCE","package":"0402","resistance":10,"tolerance_fraction":0.01,"tolerance_percent":1.0,"power_milliwatts":62.5,"power_watts":0.0625},{"lcsc":22859,"mfr":"0603WAF100JT5E","package":"0603","resistance":10,"tolerance_fraction":0.01,"tolerance_percent":1.0,"power_milliwatts":100.0,"power_watts":0.1},{"lcsc":17415,"mfr":"0805W8F100JT5E","package":"0805","resistance":10,"tolerance_fraction":0.01,"tolerance_percent":1.0,"power_milliwatts":125.0,"power_watts":0.125},{"lcsc":17903,"mfr":"1206W4F100JT5E","package":"1206","resistance":10,"tolerance_fraction":0.01,"tolerance_percent":1.0,"power_milliwatts":250.0,"power_watts":0.25},{"lcsc":22950,"mfr":"0603WAF200JT5E","package":"0603","resistance":20,"tolerance_fraction":0.01,"tolerance_percent":1.0,"power_milliwatts":100.0,"power_watts":0.1},{"lcsc":17544,"mfr":"0805W8F200JT5E","package":"0805","resistance":20,"tolerance_fraction":0.01,"tolerance_percent":1.0,"power_milliwatts":125.0,"power_watts":0.125},{"lcsc":17955,"mfr":"1206W4F200JT5E","package":"1206","resistance":20,"tolerance_fraction":0.01,"tolerance_percent":1.0,"power_milliwatts":250.0,"power_watts":0.25},{"lcsc":25092,"mfr":"0402WGF220JTCE","package":"0402","resistance":22,"tolerance_fraction":0.01,"tolerance_percent":1.0,"power_milliwatts":62.5,"power_watts":0.0625},{"lcsc":23345,"mfr":"0603WAF220JT5E","package":"0603","resistance":22,"tolerance_fraction":0.01,"tolerance_percent":1.0,"power_milliwatts":100.0,"power_watts":0.1},{"lcsc":17561,"mfr":"0805W8F220JT5E","package":"0805","resistance":22,"tolerance_fraction":0.01,"tolerance_percent":1.0,"power_milliwatts":125.0,"power_watts":0.125},{"lcsc":17958,"mfr":"1206W4F220JT5E","package":"1206","resistance":22,"tolerance_fraction":0.01,"tolerance_percent":1.0,"power_milliwatts":250.0,"power_watts":0.25},{"lcsc":25105,"mfr":"0402WGF330JTCE","package":"0402","resistance":33,"tolerance_fraction":0.01,"tolerance_percent":1.0,"power_milliwatts":62.5,"power_watts":0.0625},{"lcsc":23140,"mfr":"0603WAF330JT5E","package":"0603","resistance":33,"tolerance_fraction":0.01,"tolerance_percent":1.0,"power_milliwatts":100.0,"power_watts":0.1},{"lcsc":17634,"mfr":"0805W8F330JT5E","package":"0805","resistance":33,"tolerance_fraction":0.01,"tolerance_percent":1.0,"power_milliwatts":125.0,"power_watts":0.125},{"lcsc":23182,"mfr":"0603WAF470JT5E","package":"0603","resistance":47,"tolerance_fraction":0.01,"tolerance_percent":1.0,"power_milliwatts":100.0,"power_watts":0.1},{"lcsc":17714,"mfr":"0805W8F470JT5E","package":"0805","resistance":47,"tolerance_fraction":0.01,"tolerance_percent":1.0,"power_milliwatts":125.0,"power_watts":0.125},{"lcsc":25120,"mfr":"0402WGF499JTCE","package":"0402","resistance":49.9,"tolerance_fraction":0.01,"tolerance_percent":1.0,"power_milliwatts":62.5,"power_watts":0.0625},{"lcsc":23185,"mfr":"0603WAF499JT5E","package":"0603","resistance":49.9,"tolerance_fraction":0.01,"tolerance_percent":1.0,"power_milliwatts":100.0,"power_watts":0.1},{"lcsc":17720,"mfr":"0805W8F499JT5E","package":"0805","resistance":49.9,"tolerance_fraction":0.01,"tolerance_percent":1.0,"power_milliwatts":125.0,"power_watts":0.125},{"lcsc":23197,"mfr":"0603WAF510JT5E","package":"0603","resistance":51,"tolerance_fraction":0.01,"tolerance_percent":1.0,"power_milliwatts":100.0,"power_watts":0.1},{"lcsc":17738,"mfr":"0805W8F510JT5E","package":"0805","resistance":51,"tolerance_fraction":0.01,"tolerance_percent":1.0,"power_milliwatts":125.0,"power_watts":0.125},{"lcsc":4275,"mfr":"0603WAF750JT5E","package":"0603","resistance":75,"tolerance_fraction":0.01,"tolerance_percent":1.0,"power_milliwatts":100.0,"power_watts":0.1},{"lcsc":25076,"mfr":"0402WGF1000TCE","package":"0402","resistance":100,"tolerance_fraction":0.01,"tolerance_percent":1.0,"power_milliwatts":62.5,"power_watts":0.0625},{"lcsc":22775,"mfr":"0603WAF1000T5E","package":"0603","resistance":100,"tolerance_fraction":0.01,"tolerance_percent":1.0,"power_milliwatts":100.0,"power_watts":0.1},{"lcsc":17408,"mfr":"0805W8F1000T5E","package":"0805","resistance":100,"tolerance_fraction":0.01,"tolerance_percent":1.0,"power_milliwatts":125.0,"power_watts":0.125},{"lcsc":17901,"mfr":"1206W4F1000T5E","package":"1206","resistance":100,"tolerance_fraction":0.01,"tolerance_percent":1.0,"power_milliwatts":250.0,"power_watts":0.25},{"lcsc":25079,"mfr":"0402WGF1200TCE","package":"0402","resistance":120,"tolerance_fraction":0.01,"tolerance_percent":1.0,"power_milliwatts":62.5,"power_watts":0.0625},{"lcsc":22787,"mfr":"0603WAF1200T5E","package":"0603","resistance":120,"tolerance_fraction":0.01,"tolerance_percent":1.0,"power_milliwatts":100.0,"power_watts":0.1},{"lcsc":17437,"mfr":"0805W8F1200T5E","package":"0805","resistance":120,"tolerance_fraction":0.01,"tolerance_percent":1.0,"power_milliwatts":125.0,"power_watts":0.125},{"lcsc":17909,"mfr":"1206W4F1200T5E","package":"1206","resistance":120,"tolerance_fraction":0.01,"tolerance_percent":1.0,"power_milliwatts":250.0,"power_watts":0.25},{"lcsc":22808,"mfr":"0603WAF1500T5E","package":"0603","resistance":150,"tolerance_fraction":0.01,"tolerance_percent":1.0,"power_milliwatts":100.0,"power_watts":0.1},{"lcsc":17471,"mfr":"0805W8F1500T5E","package":"0805","resistance":150,"tolerance_fraction":0.01,"tolerance_percent":1.0,"power_milliwatts":125.0,"power_watts":0.125},{"lcsc":25087,"mfr":"0402WGF2000TCE","package":"0402","resistance":200,"tolerance_fraction":0.01,"tolerance_percent":1.0,"power_milliwatts":62.5,"power_watts":0.0625},{"lcsc":8218,"mfr":"0603WAF2000T5E","package":"0603","resistance":200,"tolerance_fraction":0.01,"tolerance_percent":1.0,"power_milliwatts":100.0,"power_watts":0.1},{"lcsc":17540,"mfr":"0805W8F2000T5E","package":"0805","resistance":200,"tolerance_fraction":0.01,"tolerance_percent":1.0,"power_milliwatts":125.0,"power_watts":0.125},{"lcsc":25091,"mfr":"0402WGF2200TCE","package":"0402","resistance":220,"tolerance_fraction":0.01,"tolerance_percent":1.0,"power_milliwatts":62.5,"power_watts":0.0625},{"lcsc":22962,"mfr":"0603WAF2200T5E","package":"0603","resistance":220,"tolerance_fraction":0.01,"tolerance_percent":1.0,"power_milliwatts":100.0,"power_watts":0.1},{"lcsc":17557,"mfr":"0805W8F2200T5E","package":"0805","resistance":220,"tolerance_fraction":0.01,"tolerance_percent":1.0,"power_milliwatts":125.0,"power_watts":0.125},{"lcsc":22966,"mfr":"0603WAF2700T5E","package":"0603","resistance":270,"tolerance_fraction":0.01,"tolerance_percent":1.0,"power_milliwatts":100.0,"power_watts":0.1},{"lcsc":23025,"mfr":"0603WAF3000T5E","package":"0603","resistance":300,"tolerance_fraction":0.01,"tolerance_percent":1.0,"power_milliwatts":100.0,"power_watts":0.1},{"lcsc":17617,"mfr":"0805W8F3000T5E","package":"0805","resistance":300,"tolerance_fraction":0.01,"tolerance_percent":1.0,"power_milliwatts":125.0,"power_watts":0.125},{"lcsc":17887,"mfr":"1206W4F3000T5E","package":"1206","resistance":300,"tolerance_fraction":0.01,"tolerance_percent":1.0,"power_milliwatts":250.0,"power_watts":0.25},{"lcsc":25104,"mfr":"0402WGF3300TCE","package":"0402","resistance":330,"tolerance_fraction":0.01,"tolerance_percent":1.0,"power_milliwatts":62.5,"power_watts":0.0625},{"lcsc":23138,"mfr":"0603WAF3300T5E","package":"0603","resistance":330,"tolerance_fraction":0.01,"tolerance_percent":1.0,"power_milliwatts":100.0,"power_watts":0.1},{"lcsc":17630,"mfr":"0805W8F3300T5E","package":"0805","resistance":330,"tolerance_fraction":0.01,"tolerance_percent":1.0,"power_milliwatts":125.0,"power_watts":0.125},{"lcsc":23151,"mfr":"0603WAF3900T5E","package":"0603","resistance":390,"tolerance_fraction":0.01,"tolerance_percent":1.0,"power_milliwatts":100.0,"power_watts":0.1},{"lcsc":17655,"mfr":"0805W8F3900T5E","package":"0805","resistance":390,"tolerance_fraction":0.01,"tolerance_percent":1.0,"power_milliwatts":125.0,"power_watts":0.125},{"lcsc":25117,"mfr":"0402WGF4700TCE","package":"0402","resistance":470,"tolerance_fraction":0.01,"tolerance_percent":1.0,"power_milliwatts":62.5,"power_watts":0.0625},{"lcsc":23179,"mfr":"0603WAF4700T5E","package":"0603","resistance":470,"tolerance_fraction":0.01,"tolerance_percent":1.0,"power_milliwatts":100.0,"power_watts":0.1},{"lcsc":17710,"mfr":"0805W8F4700T5E","package":"0805","resistance":470,"tolerance_fraction":0.01,"tolerance_percent":1.0,"power_milliwatts":125.0,"power_watts":0.125},{"lcsc":25123,"mfr":"0402WGF5100TCE","package":"0402","resistance":510,"tolerance_fraction":0.01,"tolerance_percent":1.0,"power_milliwatts":62.5,"power_watts":0.0625},{"lcsc":23193,"mfr":"0603WAF5100T5E","package":"0603","resistance":510,"tolerance_fraction":0.01,"tolerance_percent":1.0,"power_milliwatts":100.0,"power_watts":0.1},{"lcsc":17734,"mfr":"0805W8F5100T5E","package":"0805","resistance":510,"tolerance_fraction":0.01,"tolerance_percent":1.0,"power_milliwatts":125.0,"power_watts":0.125},{"lcsc":23204,"mfr":"0603WAF5600T5E","package":"0603","resistance":560,"tolerance_fraction":0.01,"tolerance_percent":1.0,"power_milliwatts":100.0,"power_watts":0.1},{"lcsc":28636,"mfr":"0805W8F5600T5E","package":"0805","resistance":560,"tolerance_fraction":0.01,"tolerance_percent":1.0,"power_milliwatts":125.0,"power_watts":0.125},{"lcsc":23228,"mfr":"0603WAF6800T5E","package":"0603","resistance":680,"tolerance_fraction":0.01,"tolerance_percent":1.0,"power_milliwatts":100.0,"power_watts":0.1},{"lcsc":17798,"mfr":"0805W8F6800T5E","package":"0805","resistance":680,"tolerance_fraction":0.01,"tolerance_percent":1.0,"power_milliwatts":125.0,"power_watts":0.125},{"lcsc":23253,"mfr":"0603WAF8200T5E","package":"0603","resistance":820,"tolerance_fraction":0.01,"tolerance_percent":1.0,"power_milliwatts":100.0,"power_watts":0.1},{"lcsc":11702,"mfr":"0402WGF1001TCE","package":"0402","resistance":1000,"tolerance_fraction":0.01,"tolerance_percent":1.0,"power_milliwatts":62.5,"power_watts":0.0625},{"lcsc":21190,"mfr":"0603WAF1001T5E","package":"0603","resistance":1000,"tolerance_fraction":0.01,"tolerance_percent":1.0,"power_milliwatts":100.0,"power_watts":0.1},{"lcsc":17513,"mfr":"0805W8F1001T5E","package":"0805","resistance":1000,"tolerance_fraction":0.01,"tolerance_percent":1.0,"power_milliwatts":125.0,"power_watts":0.125},{"lcsc":4410,"mfr":"1206W4F1001T5E","package":"1206","resistance":1000,"tolerance_fraction":0.01,"tolerance_percent":1.0,"power_milliwatts":250.0,"power_watts":0.25},{"lcsc":22765,"mfr":"0603WAF1201T5E","package":"0603","resistance":1200,"tolerance_fraction":0.01,"tolerance_percent":1.0,"power_milliwatts":100.0,"power_watts":0.1},{"lcsc":17379,"mfr":"0805W8F1201T5E","package":"0805","resistance":1200,"tolerance_fraction":0.01,"tolerance_percent":1.0,"power_milliwatts":125.0,"power_watts":0.125},{"lcsc":25867,"mfr":"0402WGF1501TCE","package":"0402","resistance":1500,"tolerance_fraction":0.01,"tolerance_percent":1.0,"power_milliwatts":62.5,"power_watts":0.0625},{"lcsc":22843,"mfr":"0603WAF1501T5E","package":"0603","resistance":1500,"tolerance_fraction":0.01,"tolerance_percent":1.0,"power_milliwatts":100.0,"power_watts":0.1},{"lcsc":4310,"mfr":"0805W8F1501T5E","package":"0805","resistance":1500,"tolerance_fraction":0.01,"tolerance_percent":1.0,"power_milliwatts":125.0,"power_watts":0.125},{"lcsc":4177,"mfr":"0603WAF1801T5E","package":"0603","resistance":1800,"tolerance_fraction":0.01,"tolerance_percent":1.0,"power_milliwatts":100.0,"power_watts":0.1},{"lcsc":4109,"mfr":"0402WGF2001TCE","package":"0402","resistance":2000,"tolerance_fraction":0.01,"tolerance_percent":1.0,"power_milliwatts":62.5,"power_watts":0.0625},{"lcsc":22975,"mfr":"0603WAF2001T5E","package":"0603","resistance":2000,"tolerance_fraction":0.01,"tolerance_percent":1.0,"power_milliwatts":100.0,"power_watts":0.1},{"lcsc":17604,"mfr":"0805W8F2001T5E","package":"0805","resistance":2000,"tolerance_fraction":0.01,"tolerance_percent":1.0,"power_milliwatts":125.0,"power_watts":0.125},{"lcsc":17944,"mfr":"1206W4F2001T5E","package":"1206","resistance":2000,"tolerance_fraction":0.01,"tolerance_percent":1.0,"power_milliwatts":250.0,"power_watts":0.25},{"lcsc":25879,"mfr":"0402WGF2201TCE","package":"0402","resistance":2200,"tolerance_fraction":0.01,"tolerance_percent":1.0,"power_milliwatts":62.5,"power_watts":0.0625},{"lcsc":4190,"mfr":"0603WAF2201T5E","package":"0603","resistance":2200,"tolerance_fraction":0.01,"tolerance_percent":1.0,"power_milliwatts":100.0,"power_watts":0.1},{"lcsc":17520,"mfr":"0805W8F2201T5E","package":"0805","resistance":2200,"tolerance_fraction":0.01,"tolerance_percent":1.0,"power_milliwatts":125.0,"power_watts":0.125},{"lcsc":22940,"mfr":"0603WAF2401T5E","package":"0603","resistance":2400,"tolerance_fraction":0.01,"tolerance_percent":1.0,"power_milliwatts":100.0,"power_watts":0.1},{"lcsc":17526,"mfr":"0805W8F2401T5E","package":"0805","resistance":2400,"tolerance_fraction":0.01,"tolerance_percent":1.0,"power_milliwatts":125.0,"power_watts":0.125},{"lcsc":13167,"mfr":"0603WAF2701T5E","package":"0603","resistance":2700,"tolerance_fraction":0.01,"tolerance_percent":1.0,"power_milliwatts":100.0,"power_watts":0.1},{"lcsc":17530,"mfr":"0805W8F2701T5E","package":"0805","resistance":2700,"tolerance_fraction":0.01,"tolerance_percent":1.0,"power_milliwatts":125.0,"power_watts":0.125},{"lcsc":4211,"mfr":"0603WAF3001T5E","package":"0603","resistance":3000,"tolerance_fraction":0.01,"tolerance_percent":1.0,"power_milliwatts":100.0,"power_watts":0.1},{"lcsc":17661,"mfr":"0805W8F3001T5E","package":"0805","resistance":3000,"tolerance_fraction":0.01,"tolerance_percent":1.0,"power_milliwatts":125.0,"power_watts":0.125},{"lcsc":25890,"mfr":"0402WGF3301TCE","package":"0402","resistance":3300,"tolerance_fraction":0.01,"tolerance_percent":1.0,"power_milliwatts":62.5,"power_watts":0.0625},{"lcsc":22978,"mfr":"0603WAF3301T5E","package":"0603","resistance":3300,"tolerance_fraction":0.01,"tolerance_percent":1.0,"power_milliwatts":100.0,"power_watts":0.1},{"lcsc":26010,"mfr":"0805W8F3301T5E","package":"0805","resistance":3300,"tolerance_fraction":0.01,"tolerance_percent":1.0,"power_milliwatts":125.0,"power_watts":0.125},{"lcsc":22980,"mfr":"0603WAF3601T5E","package":"0603","resistance":3600,"tolerance_fraction":0.01,"tolerance_percent":1.0,"power_milliwatts":100.0,"power_watts":0.1},{"lcsc":23018,"mfr":"0603WAF3901T5E","package":"0603","resistance":3900,"tolerance_fraction":0.01,"tolerance_percent":1.0,"power_milliwatts":100.0,"power_watts":0.1},{"lcsc":17614,"mfr":"0805W8F3901T5E","package":"0805","resistance":3900,"tolerance_fraction":0.01,"tolerance_percent":1.0,"power_milliwatts":125.0,"power_watts":0.125},{"lcsc":25900,"mfr":"0402WGF4701TCE","package":"0402","resistance":4700,"tolerance_fraction":0.01,"tolerance_percent":1.0,"power_milliwatts":62.5,"power_watts":0.0625},{"lcsc":23162,"mfr":"0603WAF4701T5E","package":"0603","resistance":4700,"tolerance_fraction":0.01,"tolerance_percent":1.0,"power_milliwatts":100.0,"power_watts":0.1},{"lcsc":17673,"mfr":"0805W8F4701T5E","package":"0805","resistance":4700,"tolerance_fraction":0.01,"tolerance_percent":1.0,"power_milliwatts":125.0,"power_watts":0.125},{"lcsc":17936,"mfr":"1206W4F4701T5E","package":"1206","resistance":4700,"tolerance_fraction":0.01,"tolerance_percent":1.0,"power_milliwatts":250.0,"power_watts":0.25},{"lcsc":23046,"mfr":"0603WAF4991T5E","package":"0603","resistance":4990,"tolerance_fraction":0.01,"tolerance_percent":1.0,"power_milliwatts":100.0,"power_watts":0.1},{"lcsc":25905,"mfr":"0402WGF5101TCE","package":"0402","resistance":5100,"tolerance_fraction":0.01,"tolerance_percent":1.0,"power_milliwatts":62.5,"power_watts":0.0625},{"lcsc":23186,"mfr":"0603WAF5101T5E","package":"0603","resistance":5100,"tolerance_fraction":0.01,"tolerance_percent":1.0,"power_milliwatts":100.0,"power_watts":0.1},{"lcsc":27834,"mfr":"0805W8F5101T5E","package":"0805","resistance":5100,"tolerance_fraction":0.01,"tolerance_percent":1.0,"power_milliwatts":125.0,"power_watts":0.125},{"lcsc":23189,"mfr":"0603WAF5601T5E","package":"0603","resistance":5600,"tolerance_fraction":0.01,"tolerance_percent":1.0,"power_milliwatts":100.0,"power_watts":0.1},{"lcsc":4382,"mfr":"0805W8F5601T5E","package":"0805","resistance":5600,"tolerance_fraction":0.01,"tolerance_percent":1.0,"power_milliwatts":125.0,"power_watts":0.125},{"lcsc":4260,"mfr":"0603WAF6201T5E","package":"0603","resistance":6200,"tolerance_fraction":0.01,"tolerance_percent":1.0,"power_milliwatts":100.0,"power_watts":0.1},{"lcsc":23212,"mfr":"0603WAF6801T5E","package":"0603","resistance":6800,"tolerance_fraction":0.01,"tolerance_percent":1.0,"power_milliwatts":100.0,"power_watts":0.1},{"lcsc":17772,"mfr":"0805W8F6801T5E","package":"0805","resistance":6800,"tolerance_fraction":0.01,"tolerance_percent":1.0,"power_milliwatts":125.0,"power_watts":0.125},{"lcsc":23234,"mfr":"0603WAF7501T5E","package":"0603","resistance":7500,"tolerance_fraction":0.01,"tolerance_percent":1.0,"power_milliwatts":100.0,"power_watts":0.1},{"lcsc":25981,"mfr":"0603WAF8201T5E","package":"0603","resistance":8200,"tolerance_fraction":0.01,"tolerance_percent":1.0,"power_milliwatts":100.0,"power_watts":0.1},{"lcsc":17828,"mfr":"0805W8F8201T5E","package":"0805","resistance":8200,"tolerance_fraction":0.01,"tolerance_percent":1.0,"power_milliwatts":125.0,"power_watts":0.125},{"lcsc":23260,"mfr":"0603WAF9101T5E","package":"0603","resistance":9100,"tolerance_fraction":0.01,"tolerance_percent":1.0,"power_milliwatts":100.0,"power_watts":0.1},{"lcsc":25744,"mfr":"0402WGF1002TCE","package":"0402","resistance":10000,"tolerance_fraction":0.01,"tolerance_percent":1.0,"power_milliwatts":62.5,"power_watts":0.0625},{"lcsc":25804,"mfr":"0603WAF1002T5E","package":"0603","resistance":10000,"tolerance_fraction":0.01,"tolerance_percent":1.0,"power_milliwatts":100.0,"power_watts":0.1},{"lcsc":17414,"mfr":"0805W8F1002T5E","package":"0805","resistance":10000,"tolerance_fraction":0.01,"tolerance_percent":1.0,"power_milliwatts":125.0,"power_watts":0.125},{"lcsc":17902,"mfr":"1206W4F1002T5E","package":"1206","resistance":10000,"tolerance_fraction":0.01,"tolerance_percent":1.0,"power_milliwatts":250.0,"power_watts":0.25},{"lcsc":25752,"mfr":"0402WGF1202TCE","package":"0402","resistance":12000,"tolerance_fraction":0.01,"tolerance_percent":1.0,"power_milliwatts":62.5,"power_watts":0.0625},{"lcsc":22790,"mfr":"0603WAF1202T5E","package":"0603","resistance":12000,"tolerance_fraction":0.01,"tolerance_percent":1.0,"power_milliwatts":100.0,"power_watts":0.1},{"lcsc":17444,"mfr":"0805W8F1202T5E","package":"0805","resistance":12000,"tolerance_fraction":0.01,"tolerance_percent":1.0,"power_milliwatts":125.0,"power_watts":0.125},{"lcsc":22797,"mfr":"0603WAF1302T5E","package":"0603","resistance":13000,"tolerance_fraction":0.01,"tolerance_percent":1.0,"power_milliwatts":100.0,"power_watts":0.1},{"lcsc":25756,"mfr":"0402WGF1502TCE","package":"0402","resistance":15000,"tolerance_fraction":0.01,"tolerance_percent":1.0,"power_milliwatts":62.5,"power_watts":0.0625},{"lcsc":22809,"mfr":"0603WAF1502T5E","package":"0603","resistance":15000,"tolerance_fraction":0.01,"tolerance_percent":1.0,"power_milliwatts":100.0,"power_watts":0.1},{"lcsc":17475,"mfr":"0805W8F1502T5E","package":"0805","resistance":15000,"tolerance_fraction":0.01,"tolerance_percent":1.0,"power_milliwatts":125.0,"power_watts":0.125},{"lcsc":25810,"mfr":"0603WAF1802T5E","package":"0603","resistance":18000,"tolerance_fraction":0.01,"tolerance_percent":1.0,"power_milliwatts":100.0,"power_watts":0.1},{"lcsc":25765,"mfr":"0402WGF2002TCE","package":"0402","resistance":20000,"tolerance_fraction":0.01,"tolerance_percent":1.0,"power_milliwatts":62.5,"power_watts":0.0625},{"lcsc":4184,"mfr":"0603WAF2002T5E","package":"0603","resistance":20000,"tolerance_fraction":0.01,"tolerance_percent":1.0,"power_milliwatts":100.0,"power_watts":0.1},{"lcsc":4328,"mfr":"0805W8F2002T5E","package":"0805","resistance":20000,"tolerance_fraction":0.01,"tolerance_percent":1.0,"power_milliwatts":125.0,"power_watts":0.125},{"lcsc":25768,"mfr":"0402WGF2202TCE","package":"0402","resistance":22000,"tolerance_fraction":0.01,"tolerance_percent":1.0,"power_milliwatts":62.5,"power_watts":0.0625},{"lcsc":31850,"mfr":"0603WAF2202T5E","package":"0603","resistance":22000,"tolerance_fraction":0.01,"tolerance_percent":1.0,"power_milliwatts":100.0,"power_watts":0.1},{"lcsc":17560,"mfr":"0805W8F2202T5E","package":"0805","resistance":22000,"tolerance_fraction":0.01,"tolerance_percent":1.0,"power_milliwatts":125.0,"power_watts":0.125},{"lcsc":23352,"mfr":"0603WAF2402T5E","package":"0603","resistance":24000,"tolerance_fraction":0.01,"tolerance_percent":1.0,"power_milliwatts":100.0,"power_watts":0.1},{"lcsc":17575,"mfr":"0805W8F2402T5E","package":"0805","resistance":24000,"tolerance_fraction":0.01,"tolerance_percent":1.0,"power_milliwatts":125.0,"power_watts":0.125},{"lcsc":22967,"mfr":"0603WAF2702T5E","package":"0603","resistance":27000,"tolerance_fraction":0.01,"tolerance_percent":1.0,"power_milliwatts":100.0,"power_watts":0.1},{"lcsc":17593,"mfr":"0805W8F2702T5E","package":"0805","resistance":27000,"tolerance_fraction":0.01,"tolerance_percent":1.0,"power_milliwatts":125.0,"power_watts":0.125},{"lcsc":22984,"mfr":"0603WAF3002T5E","package":"0603","resistance":30000,"tolerance_fraction":0.01,"tolerance_percent":1.0,"power_milliwatts":100.0,"power_watts":0.1},{"lcsc":17621,"mfr":"0805W8F3002T5E","package":"0805","resistance":30000,"tolerance_fraction":0.01,"tolerance_percent":1.0,"power_milliwatts":125.0,"power_watts":0.125},{"lcsc":25779,"mfr":"0402WGF3302TCE","package":"0402","resistance":33000,"tolerance_fraction":0.01,"tolerance_percent":1.0,"power_milliwatts":62.5,"power_watts":0.0625},{"lcsc":4216,"mfr":"0603WAF3302T5E","package":"0603","resistance":33000,"tolerance_fraction":0.01,"tolerance_percent":1.0,"power_milliwatts":100.0,"power_watts":0.1},{"lcsc":17633,"mfr":"0805W8F3302T5E","package":"0805","resistance":33000,"tolerance_fraction":0.01,"tolerance_percent":1.0,"power_milliwatts":125.0,"power_watts":0.125},{"lcsc":23153,"mfr":"0603WAF3902T5E","package":"0603","resistance":39000,"tolerance_fraction":0.01,"tolerance_percent":1.0,"power_milliwatts":100.0,"power_watts":0.1},{"lcsc":25792,"mfr":"0402WGF4702TCE","package":"0402","resistance":47000,"tolerance_fraction":0.01,"tolerance_percent":1.0,"power_milliwatts":62.5,"power_watts":0.0625},{"lcsc":25819,"mfr":"0603WAF4702T5E","package":"0603","resistance":47000,"tolerance_fraction":0.01,"tolerance_percent":1.0,"power_milliwatts":100.0,"power_watts":0.1},{"lcsc":17713,"mfr":"0805W8F4702T5E","package":"0805","resistance":47000,"tolerance_fraction":0.01,"tolerance_percent":1.0,"power_milliwatts":125.0,"power_watts":0.125},{"lcsc":23184,"mfr":"0603WAF4992T5E","package":"0603","resistance":49900,"tolerance_fraction":0.01,"tolerance_percent":1.0,"power_milliwatts":100.0,"power_watts":0.1},{"lcsc":25794,"mfr":"0402WGF5102TCE","package":"0402","resistance":51000,"tolerance_fraction":0.01,"tolerance_percent":1.0,"power_milliwatts":62.5,"power_watts":0.0625},{"lcsc":23196,"mfr":"0603WAF5102T5E","package":"0603","resistance":51000,"tolerance_fraction":0.01,"tolerance_percent":1.0,"power_milliwatts":100.0,"power_watts":0.1},{"lcsc":17737,"mfr":"0805W8F5102T5E","package":"0805","resistance":51000,"tolerance_fraction":0.01,"tolerance_percent":1.0,"power_milliwatts":125.0,"power_watts":0.125},{"lcsc":23206,"mfr":"0603WAF5602T5E","package":"0603","resistance":56000,"tolerance_fraction":0.01,"tolerance_percent":1.0,"power_milliwatts":100.0,"power_watts":0.1},{"lcsc":23231,"mfr":"0603WAF6802T5E","package":"0603","resistance":68000,"tolerance_fraction":0.01,"tolerance_percent":1.0,"power_milliwatts":100.0,"power_watts":0.1},{"lcsc":17801,"mfr":"0805W8F6802T5E","package":"0805","resistance":68000,"tolerance_fraction":0.01,"tolerance_percent":1.0,"power_milliwatts":125.0,"power_watts":0.125},{"lcsc":23242,"mfr":"0603WAF7502T5E","package":"0603","resistance":75000,"tolerance_fraction":0.01,"tolerance_percent":1.0,"power_milliwatts":100.0,"power_watts":0.1},{"lcsc":23254,"mfr":"0603WAF8202T5E","package":"0603","resistance":82000,"tolerance_fraction":0.01,"tolerance_percent":1.0,"power_milliwatts":100.0,"power_watts":0.1},{"lcsc":25741,"mfr":"0402WGF1003TCE","package":"0402","resistance":100000,"tolerance_fraction":0.01,"tolerance_percent":1.0,"power_milliwatts":62.5,"power_watts":0.0625},{"lcsc":25803,"mfr":"0603WAF1003T5E","package":"0603","resistance":100000,"tolerance_fraction":0.01,"tolerance_percent":1.0,"power_milliwatts":100.0,"power_watts":0.1},{"lcsc":149504,"mfr":"0805W8F1003T5E","package":"0805","resistance":100000,"tolerance_fraction":0.01,"tolerance_percent":1.0,"power_milliwatts":125.0,"power_watts":0.125},{"lcsc":17900,"mfr":"1206W4F1003T5E","package":"1206","resistance":100000,"tolerance_fraction":0.01,"tolerance_percent":1.0,"power_milliwatts":250.0,"power_watts":0.25},{"lcsc":25808,"mfr":"0603WAF1203T5E","package":"0603","resistance":120000,"tolerance_fraction":0.01,"tolerance_percent":1.0,"power_milliwatts":100.0,"power_watts":0.1},{"lcsc":22807,"mfr":"0603WAF1503T5E","package":"0603","resistance":150000,"tolerance_fraction":0.01,"tolerance_percent":1.0,"power_milliwatts":100.0,"power_watts":0.1},{"lcsc":17470,"mfr":"0805W8F1503T5E","package":"0805","resistance":150000,"tolerance_fraction":0.01,"tolerance_percent":1.0,"power_milliwatts":125.0,"power_watts":0.125},{"lcsc":25764,"mfr":"0402WGF2003TCE","package":"0402","resistance":200000,"tolerance_fraction":0.01,"tolerance_percent":1.0,"power_milliwatts":62.5,"power_watts":0.0625},{"lcsc":25811,"mfr":"0603WAF2003T5E","package":"0603","resistance":200000,"tolerance_fraction":0.01,"tolerance_percent":1.0,"power_milliwatts":100.0,"power_watts":0.1},{"lcsc":17539,"mfr":"0805W8F2003T5E","package":"0805","resistance":200000,"tolerance_fraction":0.01,"tolerance_percent":1.0,"power_milliwatts":125.0,"power_watts":0.125},{"lcsc":22961,"mfr":"0603WAF2203T5E","package":"0603","resistance":220000,"tolerance_fraction":0.01,"tolerance_percent":1.0,"power_milliwatts":100.0,"power_watts":0.1},{"lcsc":17556,"mfr":"0805W8F2203T5E","package":"0805","resistance":220000,"tolerance_fraction":0.01,"tolerance_percent":1.0,"power_milliwatts":125.0,"power_watts":0.125},{"lcsc":23024,"mfr":"0603WAF3003T5E","package":"0603","resistance":300000,"tolerance_fraction":0.01,"tolerance_percent":1.0,"power_milliwatts":100.0,"power_watts":0.1},{"lcsc":23137,"mfr":"0603WAF3303T5E","package":"0603","resistance":330000,"tolerance_fraction":0.01,"tolerance_percent":1.0,"power_milliwatts":100.0,"power_watts":0.1},{"lcsc":23178,"mfr":"0603WAF4703T5E","package":"0603","resistance":470000,"tolerance_fraction":0.01,"tolerance_percent":1.0,"power_milliwatts":100.0,"power_watts":0.1},{"lcsc":17709,"mfr":"0805W8F4703T5E","package":"0805","resistance":470000,"tolerance_fraction":0.01,"tolerance_percent":1.0,"power_milliwatts":125.0,"power_watts":0.125},{"lcsc":23192,"mfr":"0603WAF5103T5E","package":"0603","resistance":510000,"tolerance_fraction":0.01,"tolerance_percent":1.0,"power_milliwatts":100.0,"power_watts":0.1},{"lcsc":26083,"mfr":"0402WGF1004TCE","package":"0402","resistance":1000000,"tolerance_fraction":0.01,"tolerance_percent":1.0,"power_milliwatts":62.5,"power_watts":0.0625},{"lcsc":22935,"mfr":"0603WAF1004T5E","package":"0603","resistance":1000000,"tolerance_fraction":0.01,"tolerance_percent":1.0,"power_milliwatts":100.0,"power_watts":0.1},{"lcsc":17514,"mfr":"0805W8F1004T5E","package":"0805","resistance":1000000,"tolerance_fraction":0.01,"tolerance_percent":1.0,"power_milliwatts":125.0,"power_watts":0.125},{"lcsc":17927,"mfr":"1206W4F1004T5E","package":"1206","resistance":1000000,"tolerance_fraction":0.01,"tolerance_percent":1.0,"power_milliwatts":250.0,"power_watts":0.25},{"lcsc":22976,"mfr":"0603WAF2004T5E","package":"0603","resistance":2000000,"tolerance_fraction":0.01,"tolerance_percent":1.0,"power_milliwatts":100.0,"power_watts":0.1},{"lcsc":7250,"mfr":"0603WAF1005T5E","package":"0603","resistance":10000000,"tolerance_fraction":0.01,"tolerance_percent":1.0,"power_milliwatts":100.0,"power_watts":0.1}]}